narabi/__init__.py
narabi/codec.py
narabi/publisher.py
narabi/pubsub.py
narabi/topic.py
narabi/backends/__init__.py
narabi/backends/base.py
narabi/backends/redis.py
Narabi-0.2.1.dist-info/LICENSE
Narabi-0.2.1.dist-info/METADATA
Narabi-0.2.1.dist-info/WHEEL
Narabi-0.2.1.dist-info/entry_points.txt
Narabi-0.2.1.dist-info/top_level.txt
Narabi-0.2.1.dist-info/RECORD
