Metadata-Version: 2.1
Name: Narabi
Version: 0.2.1
Summary: A simple Pythonic asynchronous interface to inter-process pub/sub
Author-email: "Hong Minhee (洪 民憙)" <hong@minhee.org>
License: GNU LESSER GENERAL PUBLIC LICENSE
Project-URL: Source Code, https://github.com/dahlia/narabi
Project-URL: Issue Tracker, https://github.com/dahlia/narabi/issues
Keywords: pubsub
Classifier: Development Status :: 2 - Pre-Alpha
Classifier: Framework :: AsyncIO
Classifier: Intended Audience :: Developers
Classifier: License :: OSI Approved :: GNU Lesser General Public License v3 or later (LGPLv3+)
Classifier: Operating System :: MacOS :: MacOS X
Classifier: Operating System :: Microsoft :: Windows
Classifier: Operating System :: POSIX :: Linux
Classifier: Programming Language :: Python :: 3.10
Classifier: Programming Language :: Python :: 3.11
Classifier: Programming Language :: Python :: 3.12
Classifier: Programming Language :: Python :: 3.13
Classifier: Programming Language :: Python :: Implementation :: CPython
Classifier: Programming Language :: Python :: Implementation :: PyPy
Classifier: Topic :: Software Development :: Libraries :: Python Modules
Classifier: Typing :: Typed
Requires-Python: >=3.10
License-File: LICENSE
Provides-Extra: dev
Requires-Dist: flake8 ~=6.1.0 ; extra == 'dev'
Requires-Dist: flake8-bugbear ~=23.12.2 ; extra == 'dev'
Requires-Dist: mypy ~=1.8.0 ; extra == 'dev'
Requires-Dist: pyproject-flake8 ~=6.1.0 ; extra == 'dev'
Requires-Dist: pytest ~=7.4.3 ; extra == 'dev'
Requires-Dist: pytest-asyncio ~=0.23.2 ; extra == 'dev'
Requires-Dist: pytest-mypy ~=0.10.3 ; extra == 'dev'
Requires-Dist: types-redis >=4.2.0 ; extra == 'dev'
Provides-Extra: redis
Requires-Dist: redis[hiredis] >=4.2.0 ; extra == 'redis'
